README
setup.py
SpiNNStorageHandlers.egg-info/PKG-INFO
SpiNNStorageHandlers.egg-info/SOURCES.txt
SpiNNStorageHandlers.egg-info/dependency_links.txt
SpiNNStorageHandlers.egg-info/requires.txt
SpiNNStorageHandlers.egg-info/top_level.txt
spinn_storage_handlers/__init__.py
spinn_storage_handlers/buffered_bytearray_data_storage.py
spinn_storage_handlers/buffered_file_data_storage.py
spinn_storage_handlers/buffered_tempfile_data_storage.py
spinn_storage_handlers/exceptions.py
spinn_storage_handlers/file_data_reader.py
spinn_storage_handlers/file_data_writer.py
spinn_storage_handlers/abstract_classes/__init__.py
spinn_storage_handlers/abstract_classes/abstract_buffered_data_storage.py
spinn_storage_handlers/abstract_classes/abstract_byte_reader.py
spinn_storage_handlers/abstract_classes/abstract_byte_writer.py
spinn_storage_handlers/abstract_classes/abstract_data_reader.py
spinn_storage_handlers/abstract_classes/abstract_data_writer.py