Metadata-Version: 1.0
Name: SpiNNStorageHandlers
Version: 3.0.0
Summary: I/O handler classes for SpiNNaker software stack
Home-page: https://github.com/SpiNNakerManchester/SpiNNStorageHandlers
Author: UNKNOWN
Author-email: UNKNOWN
License: GNU GPLv3.0
Platform: UNKNOWN
